{
  "project_info": {
    "project_number": "931802532906",
    "firebase_url": "https://hammerandmole-default-rtdb.firebaseio.com",
    "project_id": "hammerandmole",
    "storage_bucket": "hammerandmole.appspot.com"
  },
  "client": [
    {
      "client_info": {
        "mobilesdk_app_id": "1:931802532906:android:ed1804cbc2b388c668c753",
        "android_client_info": {
          "package_name": "com.AlmondPawGames.HammerAndMole"
        }
      },
      "oauth_client": [],
      "api_key": [
        {
          "current_key": "AIzaSyC9I3e3wL7K33NVGtMEhjtGj-YDa9eJyss"
        }
      ],
      "services": {
        "appinvite_service": {
          "other_platform_oauth_client": []
        }
      }
    }
  ],
  "configuration_version": "1"
}